setup.cfg
setup.py
ntv_firmware/__init__.py
ntv_firmware/twisted.py
ntv_firmware.egg-info/PKG-INFO
ntv_firmware.egg-info/SOURCES.txt
ntv_firmware.egg-info/dependency_links.txt
ntv_firmware.egg-info/not-zip-safe
ntv_firmware.egg-info/top_level.txt