Metadata-Version: 1.0
Name: ntv-firmware
Version: 1.0.1
Summary: Utility function for locating the serial port of a particular firmware device.
Home-page: https://git.native.com/ntv/python-firmware
Author: Alan Pich
Author-email: alanp@native.com
License: MIT
Platform: UNKNOWN
